spdx3_build_gen/__init__.py
spdx3_build_gen/__main__.py
spdx3_build_gen/main.py
spdx3_build_gen/spdx3.py
spdx3_build_gen/version.py
spdx3_build_gen-0.0.1.dist-info/METADATA
spdx3_build_gen-0.0.1.dist-info/WHEEL
spdx3_build_gen-0.0.1.dist-info/entry_points.txt
spdx3_build_gen-0.0.1.dist-info/licenses/LICENSE
spdx3_build_gen-0.0.1.dist-info/RECORD
